auction_scraper/__init__.py
auction_scraper/abstract_models.py
auction_scraper/abstract_scraper.py
auction_scraper/scrapers/catawiki/models.py
auction_scraper/scrapers/catawiki/scraper.py
auction_scraper/scrapers/ebay/models.py
auction_scraper/scrapers/ebay/scraper.py
auction_scraper/scrapers/liveauctioneers/models.py
auction_scraper/scrapers/liveauctioneers/scraper.py
main.py
auction_scraper-0.4.2.dist-info/entry_points.txt
auction_scraper-0.4.2.dist-info/LICENSE
auction_scraper-0.4.2.dist-info/WHEEL
auction_scraper-0.4.2.dist-info/METADATA
auction_scraper-0.4.2.dist-info/RECORD
