Metadata-Version: 2.1
Name: auction-scraper
Version: 0.4.2
Summary: Extensible auction house scraper for ebay, liveauctioneers, catawiki, and other platforms
Home-page: https://github.com/dreamingspires/auction-scraper
Author: Edd Salkield
Author-email: edd@salkield.uk
Requires-Python: >=3.7,<4.0
Classifier: Programming Language :: Python :: 3
Classifier: Programming Language :: Python :: 3.7
Classifier: Programming Language :: Python :: 3.8
Classifier: Programming Language :: Python :: 3.9
Requires-Dist: babel (>=2.8.0,<3.0.0)
Requires-Dist: bs4 (>=0.0.1,<0.0.2)
Requires-Dist: datetime (>=4.3,<5.0)
Requires-Dist: pathlib (>=1.0.1,<2.0.0)
Requires-Dist: python-dateutil (>=2.8.1,<3.0.0)
Requires-Dist: requests (>=2.24.0,<3.0.0)
Requires-Dist: selenium (>=3.141.0,<4.0.0)
Requires-Dist: slimit (>=0.8.1,<0.9.0)
Requires-Dist: sqlalchemy (>=1.4.0,<2.0.0)
Requires-Dist: sqlalchemy_utils (>=0.37.8,<0.38.0)
Requires-Dist: termcolor (>=1.1.0,<2.0.0)
Requires-Dist: typer (>=0.3.2,<0.4.0)
Requires-Dist: validators (>=0.18.0,<0.19.0)
Project-URL: Repository, https://github.com/dreamingspires/auction-scraper
